setup.py
another_name_of_distributions/Binomialdistribution.py
another_name_of_distributions/Gaussiandistribution.py
another_name_of_distributions/Generaldistribution.py
another_name_of_distributions/__init__.py
another_name_of_distributions.egg-info/PKG-INFO
another_name_of_distributions.egg-info/SOURCES.txt
another_name_of_distributions.egg-info/dependency_links.txt
another_name_of_distributions.egg-info/not-zip-safe
another_name_of_distributions.egg-info/top_level.txt